social_auth_app_django-5.5.0.dist-info/licenses/LICENSE
social_django/__init__.py
social_django/admin.py
social_django/apps.py
social_django/config.py
social_django/context_processors.py
social_django/fields.py
social_django/managers.py
social_django/middleware.py
social_django/models.py
social_django/storage.py
social_django/strategy.py
social_django/urls.py
social_django/utils.py
social_django/views.py
social_django/management/__init__.py
social_django/management/commands/__init__.py
social_django/management/commands/clearsocial.py
social_django/migrations/0001_initial.py
social_django/migrations/0002_add_related_name.py
social_django/migrations/0003_alter_email_max_length.py
social_django/migrations/0004_auto_20160423_0400.py
social_django/migrations/0005_auto_20160727_2333.py
social_django/migrations/0006_partial.py
social_django/migrations/0007_code_timestamp.py
social_django/migrations/0008_partial_timestamp.py
social_django/migrations/0009_auto_20191118_0520.py
social_django/migrations/0010_uid_db_index.py
social_django/migrations/0011_alter_id_fields.py
social_django/migrations/0012_usersocialauth_extra_data_new.py
social_django/migrations/0013_migrate_extra_data.py
social_django/migrations/0014_remove_usersocialauth_extra_data.py
social_django/migrations/0015_rename_extra_data_new_usersocialauth_extra_data.py
social_django/migrations/0016_alter_usersocialauth_extra_data.py
social_django/migrations/0017_usersocialauth_user_social_auth_uid_required.py
social_django/migrations/__init__.py
social_auth_app_django-5.5.0.dist-info/METADATA
social_auth_app_django-5.5.0.dist-info/WHEEL
social_auth_app_django-5.5.0.dist-info/top_level.txt
social_auth_app_django-5.5.0.dist-info/RECORD
