Metadata-Version: 2.4
Name: social-auth-app-django
Version: 5.5.0
Summary: Python Social Authentication, Django integration.
Author-email: Matias Aguirre <matiasaguirre@gmail.com>, Michal Čihař <michal@weblate.org>
License-Expression: BSD-3-Clause
Project-URL: Changelog, https://github.com/python-social-auth/social-app-django/blob/master/CHANGELOG.md
Project-URL: Funding, https://opencollective.com/python-social-auth
Project-URL: Homepage, https://github.com/python-social-auth/social-app-django
Keywords: django,oauth,openid,saml,social auth
Classifier: Development Status :: 5 - Production/Stable
Classifier: Environment :: Web Environment
Classifier: Intended Audience :: Developers
Classifier: Programming Language :: Python :: 3
Classifier: Programming Language :: Python :: 3.10
Classifier: Programming Language :: Python :: 3.11
Classifier: Programming Language :: Python :: 3.12
Classifier: Programming Language :: Python :: 3.13
Classifier: Programming Language :: Python
Classifier: Topic :: Internet
Requires-Python: >=3.10
License-File: LICENSE
Requires-Dist: Django>=5.1
Requires-Dist: social-auth-core~=4.4
Provides-Extra: dev
Requires-Dist: coverage>=3.6; extra == "dev"
Requires-Dist: django-stubs-ext==5.2.1; extra == "dev"
Requires-Dist: django-stubs==5.2.1; extra == "dev"
Requires-Dist: mypy==1.16.1; extra == "dev"
Requires-Dist: pre-commit; extra == "dev"
Requires-Dist: pyright==1.1.402; extra == "dev"
Requires-Dist: tox; extra == "dev"
Dynamic: license-file
